LICENSE
README.md
minimata/__init__.py
minimata/chart.py
minimata/py.typed
minimata-0.1.1.dist-info/LICENSE
minimata-0.1.1.dist-info/WHEEL
minimata-0.1.1.dist-info/METADATA
minimata-0.1.1.dist-info/RECORD
