Metadata-Version: 2.1
Name: minimata
Version: 0.1.1
Summary: Minimata is a minimalist state-machine implementation.
Home-page: https://github.com/nicoolas25/minimata
Author: Nicolas Zermati
Author-email: nicoolas25@gmail.com
Requires-Python: >=3.8,<4.0
Classifier: Programming Language :: Python :: 3
Classifier: Programming Language :: Python :: 3.10
Classifier: Programming Language :: Python :: 3.8
Classifier: Programming Language :: Python :: 3.9
Requires-Dist: graphviz (>=0.20,<0.21)
Project-URL: Documentation, https://github.com/nicoolas25/minimata
Project-URL: Repository, https://github.com/nicoolas25/minimata
